jinjaninja
