Metadata-Version: 1.0
Name: jinjaninja
Version: 0.1.2
Summary: Jinja template style enforcement tool
Home-page: https://github.com/ramonsaraiva/jinjaninja
Author: Ramon Saraiva
Author-email: ramonsaraiva@gmail.com
License: MIT
Platform: UNKNOWN
